{
    "post": {
        "success": {
            "successful": true,
            "token" : "u123kf",
	"user" : {
		"id": 1,
		"email": "email@mail.ru",	
		"firstName": "Иван",
		"lastName": "Иванов",
		"paronym": "Иванович",
		"faculty": "Факультет систем управления",
		"course": 3,
		"subjects" : ["Матан", "Алгебра", "Программирование", "Философия"],
		"degree": "бакалавр",
		"about": "Самый крутой репетитор в мире :)",
		"teacher" : true ,
		"price" : 1000,
		"photo": null
	}
        },
        "error": {
            "successful": false
        }
    },
    "get": {
        "success": [
            { 
                "id": 1,
                "firstName": "Иван",
                "lastName": "Иванов",
                "paronym": "Иванович",
                "price": 1000,
                "avgMark": 3.4,
                "photo" : null
            },
            { 
                "id": 2,
                "firstName": "Александр",
                "lastName": "Логинов",
                "price": 1000,
                "avgMark": null,
                "photo" : null
            }
        ],
        "error": []
    }
}